utils/__init__.py
utils/config.py
utils/pdf.py
utils/tests/__init__.py
utils/tests/test_pdf.py
v7e_utils/__init__.py
v7e_utils/agil_connect/__init__.py
v7e_utils/agil_connect/agil_connect.py
v7e_utils/agil_connect/panel_connect.py
v7e_utils/agil_connect/rh_connect.py
v7e_utils/agil_connect/token.py
v7e_utils/agil_connect/token_wrapper.py
v7e_utils/data_helper/__init__.py
v7e_utils/data_helper/data_helper.py
v7e_utils/data_helper/error.py
v7e_utils/data_helper/record_batch.py
v7e_utils/data_utils.py
v7e_utils/dataframe_helper/__init__.py
v7e_utils/dataframe_helper/df_helper.py
v7e_utils/dataframe_helper/io.py
v7e_utils/dataframe_helper/utils.py
v7e_utils/date_utils.py
v7e_utils/file_utils.py
v7e_utils/model_utils.py
v7e_utils/report_factory/__init__.py
v7e_utils/report_factory/factory.py
v7e_utils/report_factory/loader.py
v7e_utils/report_factory/publisher.py
v7e_utils/report_factory/report_helper.py
v7e_utils/report_factory/reporter.py
v7e_utils/report_factory/runner.py
v8e_utils-0.15.1.dist-info/METADATA
v8e_utils-0.15.1.dist-info/WHEEL
v8e_utils-0.15.1.dist-info/RECORD
